MANIFEST.in
README.rst
setup.py
src/django_meio_easytags.egg-info/PKG-INFO
src/django_meio_easytags.egg-info/SOURCES.txt
src/django_meio_easytags.egg-info/dependency_links.txt
src/django_meio_easytags.egg-info/requires.txt
src/django_meio_easytags.egg-info/top_level.txt
src/easytags/__init__.py
src/easytags/library.py
src/easytags/models.py
src/easytags/node.py
src/easytags/testsettings.py
src/easytags/tests/__init__.py
src/easytags/tests/test_library.py
src/easytags/tests/test_node.py
src/easytags/tests/test_parser.py