Metadata-Version: 1.0
Name: django-meio-easytags
Version: 0.7
Summary: An easy way to create custom template tags for Django's templating system.
Home-page: http://www.meiocodigo.com/projects/django-meio-easytags/
Author: Vinicius Mendes
Author-email: vbmendes@gmail.com
License: BSD
Platform: UNKNOWN
Classifier: Development Status :: 4 - Beta
Classifier: Framework :: Django
Classifier: Intended Audience :: Developers
Classifier: License :: OSI Approved :: BSD License
Classifier: Natural Language :: English
Classifier: Operating System :: OS Independent
Classifier: Programming Language :: Python
Classifier: Topic :: Internet :: WWW/HTTP
Classifier: Topic :: Software Development :: Libraries :: Python Modules
